WeChatWorkTool/WXBizMsgCrypt3.py
WeChatWorkTool/__init__.py
WeChatWorkTool/admin.py
WeChatWorkTool/apps.py
WeChatWorkTool/ierror.py
WeChatWorkTool/models.py
WeChatWorkTool/serializers.py
WeChatWorkTool/tests.py
WeChatWorkTool/tool.py
WeChatWorkTool/urls.py
WeChatWorkTool/views.py
WeChatWorkTool/migrations/0001_initial.py
WeChatWorkTool/migrations/0002_accesstoken_appid.py
WeChatWorkTool/migrations/__init__.py
django_wechatwork_tool-0.0.3.dist-info/LICENSE
django_wechatwork_tool-0.0.3.dist-info/METADATA
django_wechatwork_tool-0.0.3.dist-info/WHEEL
django_wechatwork_tool-0.0.3.dist-info/top_level.txt
django_wechatwork_tool-0.0.3.dist-info/RECORD
