Metadata-Version: 2.1
Name: django-wechatwork-tool
Version: 0.0.3
Summary: Wechatworktool is a Django app
Home-page: https://github.com/zxj17815/wechatwork-tool
Author: iceiceice
Author-email: 597952291@qq.com
License: MIT License
Platform: UNKNOWN
Classifier: Programming Language :: Python :: 3
Classifier: License :: OSI Approved :: MIT License
Classifier: Operating System :: OS Independent
Requires-Python: >=3.6
